gleipnir/__init__.py
gleipnir/cli.py
gleipnir/commands/__init__.py
gleipnir/commands/base.py
gleipnir/commands/connect.py
gleipnir-1.2.1.dist-info/LICENSE.txt
gleipnir-1.2.1.dist-info/METADATA
gleipnir-1.2.1.dist-info/WHEEL
gleipnir-1.2.1.dist-info/entry_points.txt
gleipnir-1.2.1.dist-info/top_level.txt
gleipnir-1.2.1.dist-info/RECORD
